kpcat.py
kpcat-0.1.1.dist-info/LICENSE
kpcat-0.1.1.dist-info/METADATA
kpcat-0.1.1.dist-info/WHEEL
kpcat-0.1.1.dist-info/entry_points.txt
kpcat-0.1.1.dist-info/top_level.txt
kpcat-0.1.1.dist-info/RECORD
